microlib/__init__.py
microlib/config.py
microlib/configfile.py
microlib/data/empty_default_config.json
microlib/data/empty_default_config.toml
microlib/database.py
microlib/deprecation.py
microlib/prefs.py
microlib/terminal.py
microlib/tools.py
microlib/xdict.py
microlib-1.10.4.dist-info/LICENSE
microlib-1.10.4.dist-info/METADATA
microlib-1.10.4.dist-info/WHEEL
microlib-1.10.4.dist-info/RECORD
